{
  "url": "https://github.m6web.fr/api/v3/repos/PSG/ads-manager-psg/issues/328",
  "repository_url": "https://github.m6web.fr/api/v3/repos/PSG/ads-manager-psg",
  "labels_url": "https://github.m6web.fr/api/v3/repos/PSG/ads-manager-psg/issues/328/labels{/name}",
  "comments_url": "https://github.m6web.fr/api/v3/repos/PSG/ads-manager-psg/issues/328/comments",
  "events_url": "https://github.m6web.fr/api/v3/repos/PSG/ads-manager-psg/issues/328/events",
  "html_url": "https://github.m6web.fr/PSG/ads-manager-psg/pull/328",
  "id": 34238,
  "number": 1000,
  "title": "Alert marketing teams whene campain ROI does not reach goal",
  "user": {
    "login": "p-legallois",
    "id": 72,
    "avatar_url": "/bundles/apimock/img/p-legallois.jpg",
    "gravatar_id": "",
    "url": "https://github.m6web.fr/api/v3/users/p-legallois",
    "html_url": "https://github.m6web.fr/p-legallois",
    "followers_url": "https://github.m6web.fr/api/v3/users/p-legallois/followers",
    "following_url": "https://github.m6web.fr/api/v3/users/p-legallois/following{/other_user}",
    "gists_url": "https://github.m6web.fr/api/v3/users/p-legallois/gists{/gist_id}",
    "starred_url": "https://github.m6web.fr/api/v3/users/p-legallois/starred{/owner}{/repo}",
    "subscriptions_url": "https://github.m6web.fr/api/v3/users/p-legallois/subscriptions",
    "organizations_url": "https://github.m6web.fr/api/v3/users/p-legallois/orgs",
    "repos_url": "https://github.m6web.fr/api/v3/users/p-legallois/repos",
    "events_url": "https://github.m6web.fr/api/v3/users/p-legallois/events{/privacy}",
    "received_events_url": "https://github.m6web.fr/api/v3/users/p-legallois/received_events",
    "type": "User",
    "site_admin": false,
    "ldap_dn": "uid=t_geindre,ou=Users,dc=m6web,dc=fr"
  },
  "labels": [
    {
      "name": "failed",
      "color": "e88f8f"
    }
  ],
  "state": "open",
  "locked": false,
  "assignee": null,
  "assignees": [

  ],
  "milestone": null,
  "comments": 1,
  "created_at": "2016-12-19T13:54:21Z",
  "updated_at": "2017-01-04T13:37:31Z",
  "closed_at": null,
  "pull_request": {
    "url": "https://github.m6web.fr/api/v3/repos/PSG/ads-manager-psg/pulls/328",
    "html_url": "https://github.m6web.fr/PSG/ads-manager-psg/pull/328",
    "diff_url": "https://github.m6web.fr/PSG/ads-manager-psg/pull/328.diff",
    "patch_url": "https://github.m6web.fr/PSG/ads-manager-psg/pull/328.patch"
  },
  "body": "",
  "score": 1.0
}
